Metadata-Version: 2.1
Name: packaging-demo-hrutik
Version: 0.0.9
Summary: My package description
Author-email: Author name <some-email@gmail.com>
License: MIT
Keywords: one,two
Classifier: Programming Language :: Python :: 3
Requires-Python: >=3.7
Requires-Dist: fastapi
Provides-Extra: dev
Requires-Dist: packaging-demo-hrutik[release,static-code-qa,test]; extra == "dev"
Provides-Extra: release
Requires-Dist: twine; extra == "release"
Requires-Dist: build; extra == "release"
Provides-Extra: static-code-qa
Requires-Dist: pre-commit; extra == "static-code-qa"
Provides-Extra: test
Requires-Dist: pytest; extra == "test"
Requires-Dist: pytest-cov; extra == "test"
